{
  "items": [
    {
      "id": 1,
      "name": "Yogurt",
      "category": "Dairy",
      "isInCart": true
    },
    {
      "id": 2,
      "name": "Pomegranate",
      "category": "Produce",
      "isInCart": false
    },
    {
      "id": 3,
      "name": "Lettuce",
      "category": "Produce",
      "isInCart": true
    },
    {
      "id": 4,
      "name": "String Cheese",
      "category": "Dairy",
      "isInCart": false
    },
    {
      "id": 5,
      "name": "Swiss Cheese",
      "category": "Dairy",
      "isInCart": true
    },
    {
      "id": 6,
      "name": "Cookies",
      "category": "Dessert",
      "isInCart": false
    },
    {
      "name": "Abuja",
      "category": "Produce",
      "isInCart": true,
      "id": 7
    },
    {
      "name": "Abuja2",
      "category": "Produce",
      "isInCart": false,
      "id": 8
    },
    {
      "name": "Huawei Home Router",
      "category": "Dairy",
      "isInCart": false,
      "id": 9
    },
    {
      "name": "Abuja3",
      "category": "Produce",
      "isInCart": false,
      "id": 10
    },
    {
      "name": "HeavyMetal",
      "category": "Produce",
      "isInCart": false,
      "id": 11
    },
    {
      "name": "Drummer",
      "category": "Dessert",
      "isInCart": false,
      "id": 12
    }
  ]
}